langgate/registry/__init__.py
langgate/registry/config.py
langgate/registry/local.py
langgate/registry/models.py
langgate/registry/py.typed
langgate/registry/data/default_models.json
langgate/registry/scripts/__init__.py
langgate/registry/scripts/update_model_costs.py
langgate_registry-0.3.3.dist-info/METADATA
langgate_registry-0.3.3.dist-info/WHEEL
langgate_registry-0.3.3.dist-info/RECORD
