Metadata-Version: 2.4
Name: langgate-registry
Version: 0.3.3
Summary: Model registry implementation for LangGate AI Gateway
Author: Tanantor Ltd.
Maintainer-email: Saran Connoly <saran@tanantor.com>
License: MIT
Requires-Python: >=3.13
Requires-Dist: aiofiles<25.0.0,>=24.1.0
Requires-Dist: langgate-client==0.3.3
Requires-Dist: langgate-core==0.3.3
Requires-Dist: pydantic-settings<3.0.0,>=2.8.1
Requires-Dist: python-dotenv<0.22.0,>=0.21.1
Requires-Dist: pyyaml<7.0.0,>=6.0.1
Requires-Dist: simplejson<4.0.0,>=3.20.1
